Myfile/__init__.py
Myfile/topsis_101883071_Yogesh.py
topsis_yogesh-0.0.1.dist-info/LICENSE.lic
topsis_yogesh-0.0.1.dist-info/METADATA
topsis_yogesh-0.0.1.dist-info/WHEEL
topsis_yogesh-0.0.1.dist-info/top_level.txt
topsis_yogesh-0.0.1.dist-info/RECORD
